feincms_extensions/__init__.py
feincms_extensions/content_types.py
feincms_extensions/prepared_date.py
feincms_extensions/render_json.py
feincms_extensions/render_regions.py
feincms_extensions/templates/feincms_extensions/navigation.html
feincms_extensions/tests/__init__.py
feincms_extensions/tests/content.py
feincms_extensions/tests/factories.py
feincms_extensions/tests/models.py
feincms_extensions/tests/run.py
feincms_extensions/tests/test_content_types.py
feincms_extensions/tests/test_page_menu_navigation.py
feincms_extensions/tests/test_prepared_date.py
feincms_extensions/tests/test_render_json.py
feincms_extensions/tests/test_render_regions.py
feincms_extensions/tests/urls.py
feincms_extensions/tests/utils.py
feincms_extensions-0.7.0.dist-info/DESCRIPTION.rst
feincms_extensions-0.7.0.dist-info/METADATA
feincms_extensions-0.7.0.dist-info/RECORD
feincms_extensions-0.7.0.dist-info/WHEEL
feincms_extensions-0.7.0.dist-info/metadata.json
feincms_extensions-0.7.0.dist-info/top_level.txt
