Metadata-Version: 2.0
Name: feincms-extensions
Version: 0.7.0
Summary: UNKNOWN
Home-page: https://github.com/incuna/feincms-extensions/
Author: Incuna
Author-email: admin@incuna.com
License: UNKNOWN
Platform: UNKNOWN
Requires-Dist: FeinCMS (>=1.9,<1.11)
